vpscompass/__init__.py
vpscompass/main.py
vpscompass/prompts.py
vpscompass-2025.12.21171110.dist-info/METADATA
vpscompass-2025.12.21171110.dist-info/WHEEL
vpscompass-2025.12.21171110.dist-info/top_level.txt
vpscompass-2025.12.21171110.dist-info/RECORD
