Metadata-Version: 2.4
Name: vpscompass
Version: 2025.12.21171110
Summary: This package helps users quickly compare virtual private server (VPS) offerings by taking a simple text input—like a list of VPS providers, their plans, or key features—and returning a structured brea
Author-email: vpscompass <hi@eugene.plus>
License: MIT
Project-URL: Homepage, https://github.com/chigwell/vpscompass
Requires-Python: >=3.9
Requires-Dist: langchain-llm7>=0.0.0
Requires-Dist: llmatch-messages>=0.0.0
Requires-Dist: langchain-core>=0.3.0
